{
	"backtrace" : 4,
	"backtraceGraph" : 
	{
		"commands" : 
		[
			"add_custom_target",
			"include",
			"generate_messages"
		],
		"files" : 
		[
			"/home/methos/Documents/ros/build/tutorialPKG/cmake/tutorialPKG-genmsg.cmake",
			"/opt/ros/noetic/share/genmsg/cmake/genmsg-extras.cmake",
			"tutorialPKG/CMakeLists.txt"
		],
		"nodes" : 
		[
			{
				"file" : 2
			},
			{
				"command" : 2,
				"file" : 2,
				"line" : 75,
				"parent" : 0
			},
			{
				"command" : 1,
				"file" : 1,
				"line" : 307,
				"parent" : 1
			},
			{
				"file" : 0,
				"parent" : 2
			},
			{
				"command" : 0,
				"file" : 0,
				"line" : 21,
				"parent" : 3
			}
		]
	},
	"id" : "_tutorialPKG_generate_messages_check_deps_person_data::@0ea5ec65743f027a3d11",
	"name" : "_tutorialPKG_generate_messages_check_deps_person_data",
	"paths" : 
	{
		"build" : "tutorialPKG",
		"source" : "tutorialPKG"
	},
	"sourceGroups" : 
	[
		{
			"name" : "",
			"sourceIndexes" : 
			[
				0
			]
		},
		{
			"name" : "CMake Rules",
			"sourceIndexes" : 
			[
				1
			]
		}
	],
	"sources" : 
	[
		{
			"backtrace" : 4,
			"isGenerated" : true,
			"path" : "/home/methos/Documents/ros/build/tutorialPKG/CMakeFiles/_tutorialPKG_generate_messages_check_deps_person_data",
			"sourceGroupIndex" : 0
		},
		{
			"backtrace" : 0,
			"isGenerated" : true,
			"path" : "/home/methos/Documents/ros/build/tutorialPKG/CMakeFiles/_tutorialPKG_generate_messages_check_deps_person_data.rule",
			"sourceGroupIndex" : 1
		}
	],
	"type" : "UTILITY"
}
